model_schema_exporter/__init__.py
model_schema_exporter/cli.py
model_schema_exporter/dummy_settings.py
model_schema_exporter/exporter.py
tests/__init__.py
tests/django_test_setup.py
tests/mock_models.py
tests/test_cli.py
tests/test_exporter.py
tests/test_utils.py
model_schema_exporter-0.1.3.dist-info/LICENSE
model_schema_exporter-0.1.3.dist-info/METADATA
model_schema_exporter-0.1.3.dist-info/WHEEL
model_schema_exporter-0.1.3.dist-info/entry_points.txt
model_schema_exporter-0.1.3.dist-info/top_level.txt
model_schema_exporter-0.1.3.dist-info/RECORD
