Metadata-Version: 2.1
Name: model-schema-exporter
Version: 0.1.3
Summary: A tool to export model schemas from Django, SQLAlchemy, and FastAPI to JSON
Home-page: https://github.com/hopeatina/model-schema-exporter
Author: Hope Atina
Author-email: 
License: UNKNOWN
Platform: UNKNOWN
Classifier: Development Status :: 3 - Alpha
Classifier: Intended Audience :: Developers
Classifier: License :: OSI Approved :: MIT License
Classifier: Programming Language :: Python :: 3
Classifier: Programming Language :: Python :: 3.7
Classifier: Programming Language :: Python :: 3.8
Classifier: Programming Language :: Python :: 3.9
Requires-Python: >=3.6
Requires-Dist: click
Requires-Dist: django
Requires-Dist: sqlalchemy
Requires-Dist: fastapi
Requires-Dist: pydantic
